oathguardian/__init__.py
oathguardian/gtkui/__init__.py
oathguardian/gtkui/__main__.py
oathguardian/gtkui/actions.py
oathguardian/gtkui/application.py
oathguardian/gtkui/controllers.py
oathguardian/gtkui/datamodel.py
oathguardian/gtkui/oathguardian.xml
oathguardian/gtkui/oathguardian_menu.xml
oathguardian/gtkui/utils.py
oathguardian/oath/__init__.py
oathguardian/oath/config.py
oathguardian/oath/errors.py
oathguardian/oath/formatters.py
oathguardian/oath/keys.py
oathguardian/oath/oath.py
oathguardian/oath/uri.py
oathguardian/oath/providers/__init__.py
oathguardian/oath/providers/local.py
oathguardian/oath/providers/tools.py
oathguardian/oath/providers/yubikey.py
oathguardian/tools/__init__.py
oathguardian/tools/gnupg.py
oathguardian/tools/qrcode.py
oathguardian/tools/screenshot.py
oathguardian-0.1.0.data/data/share/applications/oathguardian.desktop
oathguardian-0.1.0.data/data/share/icons/hicolor/128x128/apps/oathguardian.png
oathguardian-0.1.0.data/data/share/icons/hicolor/16x16/apps/oathguardian.png
oathguardian-0.1.0.data/data/share/icons/hicolor/192x192/apps/oathguardian.png
oathguardian-0.1.0.data/data/share/icons/hicolor/256x256/apps/oathguardian.png
oathguardian-0.1.0.data/data/share/icons/hicolor/32x32/apps/oathguardian.png
oathguardian-0.1.0.data/data/share/icons/hicolor/48x48/apps/oathguardian.png
oathguardian-0.1.0.data/data/share/icons/hicolor/512x512/apps/oathguardian.png
oathguardian-0.1.0.data/data/share/icons/hicolor/64x64/apps/oathguardian.png
oathguardian-0.1.0.data/data/share/icons/hicolor/96x96/apps/oathguardian.png
oathguardian-0.1.0.data/data/share/icons/hicolor/scalable/apps/oathguardian.svg
oathguardian-0.1.0.dist-info/METADATA
oathguardian-0.1.0.dist-info/RECORD
oathguardian-0.1.0.dist-info/WHEEL
oathguardian-0.1.0.dist-info/entry_points.txt
oathguardian-0.1.0.dist-info/top_level.txt
