Metadata-Version: 2.1
Name: oathguardian
Version: 0.1.0
Summary: TOTP generator for Gnome
Home-page: https://framagit.org/avaiss/oathguardian
Author: Alexandre Vaissière
Author-email: avaiss@fmiw.org
License: OpenBSD
Keywords: totp authenticator oath gtk one-time-password
Platform: UNKNOWN
Classifier: Development Status :: 3 - Alpha
Classifier: Environment :: X11 Applications :: GTK
Classifier: Environment :: X11 Applications :: Gnome
Classifier: Intended Audience :: End Users/Desktop
Classifier: License :: OSI Approved :: ISC License (ISCL)
Classifier: Operating System :: POSIX :: Linux
Classifier: Programming Language :: Python :: 3 :: Only
Classifier: Topic :: Utilities
Requires-Python: ~=3.5
Requires-Dist: pyzbar (>=0.1.4)
Requires-Dist: yubikey-manager (>=0.6.0)
Requires-Dist: secretstorage (>=2.3.1)
